digitask/__init__.py
digitask/core.py
digitask-0.0.6.dist-info/METADATA
digitask-0.0.6.dist-info/WHEEL
digitask-0.0.6.dist-info/top_level.txt
digitask-0.0.6.dist-info/RECORD
