Metadata-Version: 2.4
Name: digitask
Version: 0.0.6
Summary: Add your description here
Requires-Python: >=3.12
Requires-Dist: fireworks>=2.0.5
Requires-Dist: woolworm>=0.0.9
